hunabku_kamunu/__init__.py
hunabku_kamunu/_version.py
hunabku_kamunu/endpoints/kamunu_plugin.py
Hunabku_kamunu-0.0.4a0.dist-info/METADATA
Hunabku_kamunu-0.0.4a0.dist-info/WHEEL
Hunabku_kamunu-0.0.4a0.dist-info/top_level.txt
Hunabku_kamunu-0.0.4a0.dist-info/RECORD
